[
  {
    "Stufe": 1,
    "Frage": "Was ist die Hauptstadt von Frankreich?",
    "Antwort1": "Madrid",
    "Antwort2": "Berlin",
    "Antwort3": "Paris",
    "Antwort4": "Rom",
    "RichtigeA": 3
  },
  {
    "Stufe": 1,
    "Frage": "Wie viele Finger hat eine Hand?",
    "Antwort1": "Fuenf",
    "Antwort2": "Sechs",
    "Antwort3": "Sieben",
    "Antwort4": "Vier",
    "RichtigeA": 4
  },
  {
    "Stufe": 1,
    "Frage": "Was ist die Hauptfarbe eines Stoppschilds?",
    "Antwort1": "Blau",
    "Antwort2": "Grün",
    "Antwort3": "Rot",
    "Antwort4": "Gelb",
    "RichtigeA": 3
  },
  {
    "Stufe": 2,
    "Frage": "Welches Tier ist der Koenig des Dschungels?",
    "Antwort1": "Elefant",
    "Antwort2": "Loewe",
    "Antwort3": "Giraffe",
    "Antwort4": "Zebra",
    "RichtigeA": 2
  },
  {
    "Stufe": 2,
    "Frage": "Welcher Planet ist der dritte in unserem Sonnensystem?",
    "Antwort1": "Mars",
    "Antwort2": "Erde",
    "Antwort3": "Venus",
    "Antwort4": "Jupiter",
    "RichtigeA": 2
  },
  {
    "Stufe": 2,
    "Frage": "Wie nennt man die Wissenschaft von der Erforschung der Sterne?",
    "Antwort1": "Geologie",
    "Antwort2": "Astronomie",
    "Antwort3": "Biologie",
    "Antwort4": "Chemie",
    "RichtigeA": 2
  },
  {
    "Stufe": 3,
    "Frage": "Was ist der hoechste Berg der Welt?",
    "Antwort1": "Mont Blanc",
    "Antwort2": "Mount Everest",
    "Antwort3": "Kilimandscharo",
    "Antwort4": "K2",
    "RichtigeA": 2
  },
  {
    "Stufe": 3,
    "Frage": "In welchem Land wurde der Tango geboren?",
    "Antwort1": "Spanien",
    "Antwort2": "Argentinien",
    "Antwort3": "Frankreich",
    "Antwort4": "Italien",
    "RichtigeA": 2
  },
  {
    "Stufe": 3,
    "Frage": "Welches Element hat das chemische Symbol O?",
    "Antwort1": "Eisen",
    "Antwort2": "Sauerstoff",
    "Antwort3": "Gold",
    "Antwort4": "Stickstoff",
    "RichtigeA": 2
  },
  {
    "Stufe": 4,
    "Frage": "Welches Jahr endete der Zweite Weltkrieg?",
    "Antwort1": "1945",
    "Antwort2": " 1939",
    "Antwort3": "1941",
    "Antwort4": "1948",
    "RichtigeA": 1
  },
  {
    "Stufe": 4,
    "Frage": "Wer schrieb das Buch Die Odyssee?",
    "Antwort1": "Homer",
    "Antwort2": "Shakespeare",
    "Antwort3": "Goethe",
    "Antwort4": "Dickens",
    "RichtigeA": 1
  },
  {
    "Stufe": 4,
    "Frage": "Welcher Planet wird der Rote Planet genannt?",
    "Antwort1": "Mars",
    "Antwort2": "Venus",
    "Antwort3": "Jupiter",
    "Antwort4": "Merkur",
    "RichtigeA": 1
  }
]